{
    "이미지 정보": {
        "이미지 식별자": 65048,
        "이미지 높이": 800,
        "이미지 파일명": "Joseph_039_10.jpg",
        "이미지 너비": 800
    },
    "라벨링": {
        "스타일": [
            {
                "스타일": "매니시",
                "서브스타일": "모던"
            }
        ],
        "아우터": [
            {
                "기장": "롱",
                "색상": "블랙",
                "카테고리": "베스트",
                "소매기장": "민소매",
                "소재": [
                    "우븐"
                ],
                "프린트": [
                    "무지"
                ],
                "핏": "노멀"
            }
        ],
        "하의": [
            {}
        ],
        "원피스": [
            {}
        ],
        "상의": [
            {
                "카테고리": "셔츠",
                "옷깃": "셔츠칼라",
                "소재": [
                    "우븐"
                ],
                "프린트": [
                    "무지"
                ],
                "핏": "노멀"
            }
        ]
    }
}