{
    "이미지 정보": {
        "이미지 식별자": 2312,
        "이미지 높이": 800,
        "이미지 파일명": "LIEGE_012_07.jpg",
        "이미지 너비": 800
    },
    "라벨링": {
        "스타일": [
            {
                "스타일": "스트리트",
                "서브스타일": "젠더리스"
            }
        ],
        "아우터": [
            {
                "기장": "롱",
                "색상": "베이지",
                "카테고리": "가디건",
                "디테일": [
                    "포켓",
                    "단추"
                ],
                "소매기장": "긴팔",
                "소재": [
                    "니트"
                ],
                "넥라인": "브이넥",
                "핏": "루즈"
            }
        ],
        "하의": [
            {
                "기장": "맥시",
                "색상": "블랙",
                "카테고리": "팬츠",
                "소재": [
                    "벨벳"
                ],
                "핏": "와이드"
            }
        ],
        "원피스": [
            {}
        ],
        "상의": [
            {}
        ]
    }
}