{
    "이미지 정보": {
        "이미지 식별자": 4298,
        "이미지 높이": 800,
        "이미지 파일명": "Clear_008_01.jpg",
        "이미지 너비": 800
    },
    "라벨링": {
        "스타일": [
            {
                "스타일": "로맨틱",
                "서브스타일": "스트리트"
            }
        ],
        "아우터": [
            {}
        ],
        "하의": [
            {}
        ],
        "원피스": [
            {}
        ],
        "상의": [
            {
                "기장": "롱",
                "색상": "화이트",
                "카테고리": "블라우스",
                "디테일": [
                    "러플",
                    "리본"
                ],
                "소매기장": "긴팔",
                "소재": [
                    "우븐"
                ],
                "프린트": [
                    "무지"
                ],
                "넥라인": "라운드넥",
                "핏": "루즈"
            }
        ]
    }
}